colorlookup/__init__.py
colorlookup/colors.db
colorlookup/loaddata.py
colorlookup/data/w3c_colors.txt
colorlookup/data/wiki_colors.txt
colorlookup-0.2.3.dist-info/DESCRIPTION.rst
colorlookup-0.2.3.dist-info/METADATA
colorlookup-0.2.3.dist-info/RECORD
colorlookup-0.2.3.dist-info/WHEEL
colorlookup-0.2.3.dist-info/metadata.json
colorlookup-0.2.3.dist-info/top_level.txt
