Metadata-Version: 2.0
Name: colorlookup
Version: 0.2.3
Summary: Find color values for standard W3C colors.
Home-page: https://bitbucket.org/tpodlaski/colorlookup/
Author: Tony Podlaski
Author-email: tony@podlaski.com
License: MIT
Keywords: graphics w3c web standard colors hex rgb hsv hsl
Platform: UNKNOWN
Classifier: Development Status :: 4 - Beta
Classifier: Intended Audience :: Developers
Classifier: Topic :: Multimedia :: Graphics
Classifier: Topic :: Internet :: WWW/HTTP
Classifier: License :: OSI Approved :: MIT License
Classifier: Programming Language :: Python :: 3.5
Classifier: Programming Language :: Python :: 3.6
